LFSR/lfsr.v
`timescale 1ns/1ps

module lfsr(input wire clk, reset,
            input wire [4:0] rounds,
            output reg [21:0] bitstream
            );
         
reg r1, r2, r3, r4;
wire y1, y2, y3, y4;
reg [3:0] seed;
wire y5;
reg [4:0] counter;

always @(posedge clk)   begin
    if (reset)  begin
        seed = 4'b1110;
        r1 <= seed[3];
        r2 <= seed[2];
        r3 <= seed[1];
        r4 <= seed[0];
        counter <= rounds;
        bitstream <= 0;
    end
    if (~counter) begin
        r1 <= y5;
        r2 <= y1;
        r3 <= y2;
        r4 <= y3;
        counter = counter - 1'b1;
    bitstream = {bitstream[21:1],r4};
    bitstream = bitstream << 1;
    end
end
  

assign y1 = r1;
assign y2 = r2;
assign y3 = r3;
assign y4 = r4;
assign y5 = r1 ^ r2 ^ r4;
    
endmodule

LFSR/tb.v
`timescale 1ns/1ps
module lfsr_tb;

  //Ports
  reg clk, reset;
  reg [4:0] rounds;
  wire [21:0] bitstream;

  lfsr  lfsr_inst (
    .clk(clk),
    .reset(reset),
    .rounds(rounds),
    .bitstream(bitstream)
  );

    always #5  clk = ! clk ;
    initial begin  
    $dumpfile("dump.vcd");
    $dumpvars(0,lfsr_tb);
    rounds = 20;
    reset = 1; clk = 0;
    #7 reset = 0;
    #250
    $finish;
end
endmodule

LFSR/dump.vcd
$date
	Tue Mar 05 20:33:07 2024
$end
$version
	Icarus Verilog
$end
$timescale
	1ps
$end
$scope module lfsr_tb $end
$var wire 22 ! bitstream [21:0] $end
$var reg 1 " clk $end
$var reg 1 # reset $end
$var reg 5 $ rounds [4:0] $end
$scope module lfsr_inst $end
$var wire 1 " clk $end
$var wire 1 # reset $end
$var wire 5 % rounds [4:0] $end
$var wire 1 & y1 $end
$var wire 1 ' y2 $end
$var wire 1 ( y3 $end
$var wire 1 ) y4 $end
$var wire 1 * y5 $end
$var reg 22 + bitstream [21:0] $end
$var reg 5 , counter [4:0] $end
$var reg 1 - r1 $end
$var reg 1 . r2 $end
$var reg 1 / r3 $end
$var reg 1 0 r4 $end
$var reg 4 1 seed [3:0] $end
$upscope $end
$upscope $end
$enddefinitions $end
$comment Show the parameter values. $end
$dumpall
$end
#0
$dumpvars
bx 1
x0
x/
x.
x-
bx ,
bx +
x*
x)
x(
x'
x&
b10100 %
b10100 $
1#
0"
bx !
$end
#5000
0*
b0 !
b0 +
b10100 ,
0)
00
1(
1/
1'
1.
1&
1-
b1110 1
1"
#7000
0#
#10000
0"
#15000
1)
10
0&
0-
b10011 ,
1"
#20000
0"
#25000
1*
0'
0.
b10 !
b10 +
b10010 ,
1"
#30000
0"
#35000
0*
0(
0/
1&
1-
b110 !
b110 +
b10001 ,
1"
#40000
0"
#45000
1*
0)
00
1'
1.
0&
0-
b1110 !
b1110 +
b10000 ,
1"
#50000
0"
#55000
1(
1/
0'
0.
1&
1-
b11100 !
b11100 +
b1111 ,
1"
#60000
0"
#65000
1)
10
0(
0/
1'
1.
b111000 !
b111000 +
b1110 ,
1"
#70000
0"
#75000
0*
0)
00
1(
1/
b1110010 !
b1110010 +
b1101 ,
1"
#80000
0"
#85000
1)
10
0&
0-
b11100100 !
b11100100 +
b1100 ,
1"
#90000
0"
#95000
1*
0'
0.
b111001010 !
b111001010 +
b1011 ,
1"
#100000
0"
#105000
0*
0(
0/
1&
1-
b1110010110 !
b1110010110 +
b1010 ,
1"
#110000
0"
#115000
1*
0)
00
1'
1.
0&
0-
b11100101110 !
b11100101110 +
b1001 ,
1"
#120000
0"
#125000
1(
1/
0'
0.
1&
1-
b111001011100 !
b111001011100 +
b1000 ,
1"
#130000
0"
#135000
1)
10
0(
0/
1'
1.
b1110010111000 !
b1110010111000 +
b111 ,
1"
#140000
0"
#145000
0*
0)
00
1(
1/
b11100101110010 !
b11100101110010 +
b110 ,
1"
#150000
0"
#155000
1)
10
0&
0-
b111001011100100 !
b111001011100100 +
b101 ,
1"
#160000
0"
#165000
1*
0'
0.
b1110010111001010 !
b1110010111001010 +
b100 ,
1"
#170000
0"
#175000
0*
0(
0/
1&
1-
b11100101110010110 !
b11100101110010110 +
b11 ,
1"
#180000
0"
#185000
1*
0)
00
1'
1.
0&
0-
b111001011100101110 !
b111001011100101110 +
b10 ,
1"
#190000
0"
#195000
1(
1/
0'
0.
1&
1-
b1110010111001011100 !
b1110010111001011100 +
b1 ,
1"
#200000
0"
#205000
1)
10
0(
0/
1'
1.
b11100101110010111000 !
b11100101110010111000 +
b0 ,
1"
#210000
0"
#215000
0*
0)
00
1(
1/
b111001011100101110010 !
b111001011100101110010 +
b11111 ,
1"
